MANIFEST.in
dodo
dodo.py
setup.py
dodopie.egg-info/PKG-INFO
dodopie.egg-info/SOURCES.txt
dodopie.egg-info/dependency_links.txt
dodopie.egg-info/top_level.txt