Metadata-Version: 1.1
Name: dodopie
Version: 0.98
Summary: Task Management for Hackers
Home-page: http://atmb4u.github.io/dodo
Author: Anoop Thomas Mathew
Author-email: atmb4u@gmail.com
License: BSD
Platform: UNKNOWN
Classifier: Programming Language :: Python
Classifier: Programming Language :: Python :: 2.7
Classifier: License :: OSI Approved :: BSD License
Classifier: Operating System :: OS Independent
Classifier: Intended Audience :: Developers
Classifier: Environment :: Console
Classifier: Topic :: Software Development :: Libraries :: Python Modules
